nonebot_plugin_splatoon3_schedule/__init__.py
nonebot_plugin_splatoon3_schedule/check.py
nonebot_plugin_splatoon3_schedule/config.py
nonebot_plugin_splatoon3_schedule/data/__init__.py
nonebot_plugin_splatoon3_schedule/data/data_source.py
nonebot_plugin_splatoon3_schedule/data/db_control.py
nonebot_plugin_splatoon3_schedule/data/db_image.py
nonebot_plugin_splatoon3_schedule/data/static_data_getter.py
nonebot_plugin_splatoon3_schedule/image/__init__.py
nonebot_plugin_splatoon3_schedule/image/image.py
nonebot_plugin_splatoon3_schedule/image/image_processer.py
nonebot_plugin_splatoon3_schedule/image/image_processer_tools.py
nonebot_plugin_splatoon3_schedule/resource/ImageData/10024.png
nonebot_plugin_splatoon3_schedule/resource/ImageData/10025.ico
nonebot_plugin_splatoon3_schedule/resource/ImageData/10026.png
nonebot_plugin_splatoon3_schedule/resource/ImageData/AREA.png
nonebot_plugin_splatoon3_schedule/resource/ImageData/CLAM.png
nonebot_plugin_splatoon3_schedule/resource/ImageData/Cohozuna.png
nonebot_plugin_splatoon3_schedule/resource/ImageData/GOAL.png
nonebot_plugin_splatoon3_schedule/resource/ImageData/Horrorboros.png
nonebot_plugin_splatoon3_schedule/resource/ImageData/LOFT.png
nonebot_plugin_splatoon3_schedule/resource/ImageData/Megalodontia.png
nonebot_plugin_splatoon3_schedule/resource/ImageData/Random.png
nonebot_plugin_splatoon3_schedule/resource/ImageData/Ranked-Challenge.png
nonebot_plugin_splatoon3_schedule/resource/ImageData/Ranked-Open.png
nonebot_plugin_splatoon3_schedule/resource/ImageData/Ranked.png
nonebot_plugin_splatoon3_schedule/resource/ImageData/Regular.png
nonebot_plugin_splatoon3_schedule/resource/ImageData/TURF_WAR.png
nonebot_plugin_splatoon3_schedule/resource/ImageData/Triumvirate.png
nonebot_plugin_splatoon3_schedule/resource/ImageData/X.png
nonebot_plugin_splatoon3_schedule/resource/ImageData/bg.png
nonebot_plugin_splatoon3_schedule/resource/ImageData/bg2.png
nonebot_plugin_splatoon3_schedule/resource/ImageData/bg3.png
nonebot_plugin_splatoon3_schedule-2.0.6.dist-info/METADATA
nonebot_plugin_splatoon3_schedule-2.0.6.dist-info/WHEEL
nonebot_plugin_splatoon3_schedule-2.0.6.dist-info/licenses/LICENSE
nonebot_plugin_splatoon3_schedule-2.0.6.dist-info/RECORD
