Metadata-Version: 2.4
Name: nonebot-plugin-splatoon3-schedule
Version: 2.0.6
Summary: 一个基于nonebot2框架的splatoon3游戏日程查询插件
License-File: LICENSE
Author: cypas
Author-email: ayano05@outlook.com
Requires-Python: >=3.9,<4.0
Classifier: Programming Language :: Python :: 3
Classifier: Programming Language :: Python :: 3.9
Classifier: Programming Language :: Python :: 3.10
Classifier: Programming Language :: Python :: 3.11
Classifier: Programming Language :: Python :: 3.12
Classifier: Programming Language :: Python :: 3.13
Classifier: Programming Language :: Python :: 3.14
Requires-Dist: Pillow (>=11.3.0,<12.0.0)
Requires-Dist: beautifulsoup4 (>=4.12.2,<5.0.0)
Requires-Dist: cloudscraper (>=1.2.71,<2.0.0)
Requires-Dist: cos_python_sdk_v5 (>=1.9.30,<2.0.0)
Requires-Dist: httpx (>=0.28.1,<0.29.0)
Requires-Dist: nonebot-adapter-kaiheila (>=0.3.4,<0.4.0)
Requires-Dist: nonebot-adapter-onebot (>=2.4.6,<3.0.0)
Requires-Dist: nonebot-adapter-qq (>=1.6.6,<2.0.0)
Requires-Dist: nonebot-adapter-telegram (>=0.1.0b20,<0.2.0)
Requires-Dist: nonebot-plugin-apscheduler (>=0.5.0,<0.6.0)
Requires-Dist: nonebot2 (>=2.4.4,<3.0.0)
Requires-Dist: nonebot_plugin_datastore (>=1.3.0,<2.0.0)
Requires-Dist: playwright (>=1.40.0,<2.0.0)
Requires-Dist: pydantic (>=1.0.0,<3.0.0,!=2.5.0,!=2.5.1)
